gemspa_spt/__init__.py
gemspa_spt/particle_tracks.py
gemspa_spt-0.0.3.dist-info/LICENSE
gemspa_spt-0.0.3.dist-info/METADATA
gemspa_spt-0.0.3.dist-info/WHEEL
gemspa_spt-0.0.3.dist-info/top_level.txt
gemspa_spt-0.0.3.dist-info/RECORD
