Metadata-Version: 2.1
Name: gemspa-spt
Version: 0.0.3
Summary: A package for analysis of single particle tracking experiments
Author-email: Sarah Keegan <sarah.keegan@nyulangone.org>
License: BSD 3-Clause License
Project-URL: Homepage, https://github.com/liamholtlab/gemspa-spt
Project-URL: Bug Tracker, https://github.com/liamholtlab/gemspa-spt/issues
Classifier: Programming Language :: Python :: 3
Classifier: License :: OSI Approved :: BSD License
Classifier: Operating System :: OS Independent
Requires-Python: >=3.8
License-File: LICENSE
Requires-Dist: numpy
Requires-Dist: pandas
Requires-Dist: scipy
